LICENSE
README.md
setup.py
funcsforspo_l.egg-info/PKG-INFO
funcsforspo_l.egg-info/SOURCES.txt
funcsforspo_l.egg-info/dependency_links.txt
funcsforspo_l.egg-info/requires.txt
funcsforspo_l.egg-info/top_level.txt
funcsforspo_l/femails/__init__.py
funcsforspo_l/femails/femails.py
funcsforspo_l/fexceptions/__init__.py
funcsforspo_l/fexceptions/exceptions.py
funcsforspo_l/fftp/__init__.py
funcsforspo_l/fftp/fftp.py
funcsforspo_l/fopenpyxl/__init__.py
funcsforspo_l/fopenpyxl/openpyxl_funcs.py
funcsforspo_l/fpdf/base/base.py
funcsforspo_l/fpdf/fcompress/__compress_online.py
funcsforspo_l/fpdf/fcompress/__init__.py
funcsforspo_l/fpdf/fcompress/compress.py
funcsforspo_l/fpdf/fhtml_to_pdf/__html_to_pdf.py
funcsforspo_l/fpdf/fhtml_to_pdf/__init__.py
funcsforspo_l/fpdf/fhtml_to_pdf/html_to_pdf.py
funcsforspo_l/fpdf/fimgpdf/img_to_pdf.py
funcsforspo_l/fpdf/focr/__init__.py
funcsforspo_l/fpdf/focr/__ocr_online.py
funcsforspo_l/fpdf/focr/orc.py
funcsforspo_l/fpdf/pdftoxlsx/pdftoxlsx.py
funcsforspo_l/fpysimplegui/__init__.py
funcsforspo_l/fpysimplegui/functions_for_sg.py
funcsforspo_l/fpython/__init__.py
funcsforspo_l/fpython/functions_for_py.py
funcsforspo_l/fregex/__init__.py
funcsforspo_l/fregex/functions_re.py
funcsforspo_l/fselenium/__init__.py
funcsforspo_l/fselenium/functions_selenium.py
funcsforspo_l/fsqlite/__init__.py
funcsforspo_l/fsqlite/sqlite_functions.py