Metadata-Version: 2.1
Name: funcsforspo-l
Version: 2.1.1
Summary: Funções Para Melhorar Desenvolvimento de Robôs com Selenium - Linux
Home-page: https://github.com/githubpaycon/funcsforspo_l
Author: Gabriel Lopes de Souza
Author-email: githubpaycon@gmail.com
License: MIT License
Keywords: Funções Para Melhorar Desenvolvimento de Robôs com Selenium - Linux
License-File: LICENSE
